{
  "data": [
    {
      "id": "nz-sa-t20-3",
      "matchType": "T20I",
      "status": "Match not started",
      "venue": "Saxton Oval, Nelson",
      "date": "2026-03-21",
      "dateTimeGMT": "2026-03-21T06:00:00",
      "t1": "New Zealand",
      "t2": "South Africa",
      "t1s": "",
      "t2s": "",
      "matchStarted": false,
      "matchEnded": false,
      "series_id": "sa-nz-2026",
      "name": "New Zealand vs South Africa, 3rd T20I"
    },
    {
      "id": "eng-nz-test1-2026",
      "matchType": "Test",
      "status": "Match not started",
      "venue": "Lord's Cricket Ground, London",
      "date": "2026-06-04",
      "dateTimeGMT": "2026-06-04T10:00:00",
      "t1": "England",
      "t2": "New Zealand",
      "t1s": "",
      "t2s": "",
      "matchStarted": false,
      "matchEnded": false,
      "series_id": "nz-eng-2026",
      "name": "England vs New Zealand, 1st Test"
    },
    {
      "id": "ind-afg-test-2026",
      "matchType": "Test",
      "status": "Match not started",
      "venue": "M. Chinnaswamy Stadium, Bengaluru",
      "date": "2026-06-06",
      "dateTimeGMT": "2026-06-06T04:00:00",
      "t1": "India",
      "t2": "Afghanistan",
      "t1s": "",
      "t2s": "",
      "matchStarted": false,
      "matchEnded": false,
      "series_id": "afg-ind-2026",
      "name": "India vs Afghanistan, Only Test"
    },
    {
      "id": "ind-afg-odi1-2026",
      "matchType": "ODI",
      "status": "Match not started",
      "venue": "Rajiv Gandhi Int. Stadium, Hyderabad",
      "date": "2026-06-10",
      "dateTimeGMT": "2026-06-10T09:00:00",
      "t1": "India",
      "t2": "Afghanistan",
      "t1s": "",
      "t2s": "",
      "matchStarted": false,
      "matchEnded": false,
      "series_id": "afg-ind-2026",
      "name": "India vs Afghanistan, 1st ODI"
    },
    {
      "id": "eng-nz-test2-2026",
      "matchType": "Test",
      "status": "Match not started",
      "venue": "Trent Bridge, Nottingham",
      "date": "2026-06-12",
      "dateTimeGMT": "2026-06-12T10:00:00",
      "t1": "England",
      "t2": "New Zealand",
      "t1s": "",
      "t2s": "",
      "matchStarted": false,
      "matchEnded": false,
      "series_id": "nz-eng-2026",
      "name": "England vs New Zealand, 2nd Test"
    },
    {
      "id": "ind-afg-odi2-2026",
      "matchType": "ODI",
      "status": "Match not started",
      "venue": "JSCA International Stadium, Ranchi",
      "date": "2026-06-13",
      "dateTimeGMT": "2026-06-13T09:00:00",
      "t1": "India",
      "t2": "Afghanistan",
      "t1s": "",
      "t2s": "",
      "matchStarted": false,
      "matchEnded": false,
      "series_id": "afg-ind-2026",
      "name": "India vs Afghanistan, 2nd ODI"
    },
    {
      "id": "ind-afg-odi3-2026",
      "matchType": "ODI",
      "status": "Match not started",
      "venue": "Punjab Cricket Association Stadium, Mohali",
      "date": "2026-06-16",
      "dateTimeGMT": "2026-06-16T09:00:00",
      "t1": "India",
      "t2": "Afghanistan",
      "t1s": "",
      "t2s": "",
      "matchStarted": false,
      "matchEnded": false,
      "series_id": "afg-ind-2026",
      "name": "India vs Afghanistan, 3rd ODI"
    },
    {
      "id": "eng-nz-test3-2026",
      "matchType": "Test",
      "status": "Match not started",
      "venue": "Headingley, Leeds",
      "date": "2026-06-25",
      "dateTimeGMT": "2026-06-25T10:00:00",
      "t1": "England",
      "t2": "New Zealand",
      "t1s": "",
      "t2s": "",
      "matchStarted": false,
      "matchEnded": false,
      "series_id": "nz-eng-2026",
      "name": "England vs New Zealand, 3rd Test"
    },
    {
      "id": "eng-ind-t20-1-2026",
      "matchType": "T20I",
      "status": "Match not started",
      "venue": "Edgbaston, Birmingham",
      "date": "2026-07-01",
      "dateTimeGMT": "2026-07-01T17:30:00",
      "t1": "England",
      "t2": "India",
      "t1s": "",
      "t2s": "",
      "matchStarted": false,
      "matchEnded": false,
      "series_id": "ind-eng-2026",
      "name": "England vs India, 1st T20I"
    },
    {
      "id": "eng-ind-t20-2-2026",
      "matchType": "T20I",
      "status": "Match not started",
      "venue": "Lord's Cricket Ground, London",
      "date": "2026-07-04",
      "dateTimeGMT": "2026-07-04T17:30:00",
      "t1": "England",
      "t2": "India",
      "t1s": "",
      "t2s": "",
      "matchStarted": false,
      "matchEnded": false,
      "series_id": "ind-eng-2026",
      "name": "England vs India, 2nd T20I"
    },
    {
      "id": "eng-ind-t20-3-2026",
      "matchType": "T20I",
      "status": "Match not started",
      "venue": "The Oval, London",
      "date": "2026-07-07",
      "dateTimeGMT": "2026-07-07T17:30:00",
      "t1": "England",
      "t2": "India",
      "t1s": "",
      "t2s": "",
      "matchStarted": false,
      "matchEnded": false,
      "series_id": "ind-eng-2026",
      "name": "England vs India, 3rd T20I"
    },
    {
      "id": "eng-ind-t20-4-2026",
      "matchType": "T20I",
      "status": "Match not started",
      "venue": "Old Trafford, Manchester",
      "date": "2026-07-11",
      "dateTimeGMT": "2026-07-11T17:30:00",
      "t1": "England",
      "t2": "India",
      "t1s": "",
      "t2s": "",
      "matchStarted": false,
      "matchEnded": false,
      "series_id": "ind-eng-2026",
      "name": "England vs India, 4th T20I"
    },
    {
      "id": "eng-ind-t20-5-2026",
      "matchType": "T20I",
      "status": "Match not started",
      "venue": "Sophia Gardens, Cardiff",
      "date": "2026-07-14",
      "dateTimeGMT": "2026-07-14T17:30:00",
      "t1": "England",
      "t2": "India",
      "t1s": "",
      "t2s": "",
      "matchStarted": false,
      "matchEnded": false,
      "series_id": "ind-eng-2026",
      "name": "England vs India, 5th T20I"
    },
    {
      "id": "eng-ind-odi-1-2026",
      "matchType": "ODI",
      "status": "Match not started",
      "venue": "Headingley, Leeds",
      "date": "2026-07-17",
      "dateTimeGMT": "2026-07-17T10:30:00",
      "t1": "England",
      "t2": "India",
      "t1s": "",
      "t2s": "",
      "matchStarted": false,
      "matchEnded": false,
      "series_id": "ind-eng-2026",
      "name": "England vs India, 1st ODI"
    },
    {
      "id": "eng-ind-odi-2-2026",
      "matchType": "ODI",
      "status": "Match not started",
      "venue": "Bristol County Ground",
      "date": "2026-07-20",
      "dateTimeGMT": "2026-07-20T10:30:00",
      "t1": "England",
      "t2": "India",
      "t1s": "",
      "t2s": "",
      "matchStarted": false,
      "matchEnded": false,
      "series_id": "ind-eng-2026",
      "name": "England vs India, 2nd ODI"
    },
    {
      "id": "eng-ind-odi-3-2026",
      "matchType": "ODI",
      "status": "Match not started",
      "venue": "Trent Bridge, Nottingham",
      "date": "2026-07-23",
      "dateTimeGMT": "2026-07-23T10:30:00",
      "t1": "England",
      "t2": "India",
      "t1s": "",
      "t2s": "",
      "matchStarted": false,
      "matchEnded": false,
      "series_id": "ind-eng-2026",
      "name": "England vs India, 3rd ODI"
    },
    {
      "id": "sa-aus-test1-2026",
      "matchType": "Test",
      "status": "Match not started",
      "venue": "Newlands, Cape Town",
      "date": "2026-09-24",
      "dateTimeGMT": "2026-09-24T08:00:00",
      "t1": "South Africa",
      "t2": "Australia",
      "t1s": "",
      "t2s": "",
      "matchStarted": false,
      "matchEnded": false,
      "series_id": "aus-sa-2026",
      "name": "South Africa vs Australia, 1st Test"
    },
    {
      "id": "sa-aus-test2-2026",
      "matchType": "Test",
      "status": "Match not started",
      "venue": "St George's Park, Gqeberha",
      "date": "2026-10-02",
      "dateTimeGMT": "2026-10-02T08:00:00",
      "t1": "South Africa",
      "t2": "Australia",
      "t1s": "",
      "t2s": "",
      "matchStarted": false,
      "matchEnded": false,
      "series_id": "aus-sa-2026",
      "name": "South Africa vs Australia, 2nd Test"
    },
    {
      "id": "sa-aus-odi1-2026",
      "matchType": "ODI",
      "status": "Match not started",
      "venue": "Wanderers, Johannesburg",
      "date": "2026-10-10",
      "dateTimeGMT": "2026-10-10T11:00:00",
      "t1": "South Africa",
      "t2": "Australia",
      "t1s": "",
      "t2s": "",
      "matchStarted": false,
      "matchEnded": false,
      "series_id": "aus-sa-2026",
      "name": "South Africa vs Australia, 1st ODI"
    },
    {
      "id": "nz-sa-t20-2",
      "matchType": "T20I",
      "status": "New Zealand won by 68 runs",
      "venue": "Seddon Park, Hamilton",
      "date": "2026-03-17",
      "dateTimeGMT": "2026-03-17T00:00:00",
      "t1": "New Zealand",
      "t2": "South Africa",
      "t1s": "175/6 (20ov)",
      "t2s": "107/10 (15.3ov)",
      "matchStarted": true,
      "matchEnded": true,
      "series_id": "sa-nz-2026",
      "name": "New Zealand vs South Africa, 2nd T20I"
    },
    {
      "id": "ban-pak-odi-1",
      "matchType": "ODI",
      "status": "Bangladesh won by 11 runs",
      "venue": "Shere Bangla National Stadium, Dhaka",
      "date": "2026-03-16",
      "dateTimeGMT": "2026-03-16T09:00:00",
      "t1": "Bangladesh",
      "t2": "Pakistan",
      "t1s": "298/7 (50ov)",
      "t2s": "287/9 (50ov)",
      "matchStarted": true,
      "matchEnded": true,
      "series_id": "ban-pak-2026",
      "name": "Bangladesh vs Pakistan, 1st ODI"
    },
    {
      "id": "nz-sa-t20-1",
      "matchType": "T20I",
      "status": "South Africa won by 7 wkts",
      "venue": "Eden Park, Auckland",
      "date": "2026-03-14",
      "dateTimeGMT": "2026-03-14T06:00:00",
      "t1": "New Zealand",
      "t2": "South Africa",
      "t1s": "167/8 (20ov)",
      "t2s": "168/3 (17.2ov)",
      "matchStarted": true,
      "matchEnded": true,
      "series_id": "sa-nz-2026",
      "name": "New Zealand vs South Africa, 1st T20I"
    }
  ],
  "fetched_at": "2026-03-20T01:04:55.393361+00:00",
  "source": "icc_calendar"
}